{
  "cli": {
    "version": ">= 5.9.0"
  },
  "build": {
    "development": {
      "developmentClient": true,
      "distribution": "internal",
      "android": {
        "buildType": "apk",
        "gradleCommand": ":app:assembleRelease"
      },
      "ios": {
        "simulator": false
      },
      "env": {
        "VERYFI_CLIENT_ID": "your-veryfi-client-id",
        "VERYFI_CLIENT_SECRET": "your-veryfi-client-secret",
        "VERYFI_API_KEY": "your-veryfi-api-key",
        "VERYFI_USERNAME": "your-veryfi-username"
      }
    },
    "preview": {
      "distribution": "internal",
      "android": {
        "buildType": "apk"
      },
      "env": {
        "VERYFI_CLIENT_ID": "your-veryfi-client-id",
        "VERYFI_CLIENT_SECRET": "your-veryfi-client-secret",
        "VERYFI_API_KEY": "your-veryfi-api-key",
        "VERYFI_USERNAME": "your-veryfi-username"
      }
    },
    "production": {
      "android": {
        "buildType": "app-bundle"
      }
    }
  },
  "submit": {
    "production": {}
  }
}
